oldNeuralNetworks/__init__.py
oldNeuralNetworks/oldNeuralNetworks.py
oldNeuralNetworks-0.0.1.dist-info/METADATA
oldNeuralNetworks-0.0.1.dist-info/WHEEL
oldNeuralNetworks-0.0.1.dist-info/top_level.txt
oldNeuralNetworks-0.0.1.dist-info/RECORD
